{"nm":"scene1","ddd":0,"h":40,"w":40,"meta":{"g":"@lottiefiles/creator 0.48.0"},"layers":[{"ty":4,"nm":"Polygon 1","sr":1,"st":0,"op":60,"ip":0,"hd":false,"ddd":0,"bm":0,"hasMask":false,"ao":0,"ks":{"a":{"a":0,"k":[0,25]},"s":{"a":1,"k":[{"o":{"x":0.167,"y":0.167},"i":{"x":0.833,"y":0.833},"s":[24.552103762322012,0],"t":0},{"o":{"x":0.167,"y":0.167},"i":{"x":0.833,"y":0.833},"s":[24.552103762322012,3],"t":20},{"s":[24.552103762322012,24.783973312258635],"t":40}]},"sk":{"a":0,"k":0},"p":{"a":0,"k":[10.90000000000001,40.793989992097]},"r":{"a":0,"k":0},"sa":{"a":0,"k":0},"o":{"a":1,"k":[{"o":{"x":0.167,"y":0.167},"i":{"x":0.833,"y":0.833},"s":[100],"t":0},{"o":{"x":0.167,"y":0.167},"i":{"x":0.833,"y":0.833},"s":[100],"t":20},{"o":{"x":0.167,"y":0.167},"i":{"x":0.833,"y":0.833},"s":[100],"t":40},{"s":[0],"t":61}]}},"ef":[],"shapes":[{"ty":"gr","bm":0,"hd":false,"nm":"Group","it":[{"ty":"sr","bm":0,"hd":false,"nm":"Polygon Path 1","d":1,"pt":{"a":0,"k":3},"p":{"a":0,"k":[0,0]},"or":{"a":0,"k":50},"os":{"a":0,"k":0},"r":{"a":0,"k":0},"sy":2},{"ty":"fl","bm":0,"hd":false,"nm":"Fill","c":{"a":0,"k":[0.7373,0.9333,1]},"r":2,"o":{"a":0,"k":50}},{"ty":"tr","a":{"a":0,"k":[0,-12.5]},"s":{"a":0,"k":[100,100]},"sk":{"a":0,"k":0},"p":{"a":0,"k":[0,-12.5]},"r":{"a":0,"k":0},"sa":{"a":0,"k":0},"o":{"a":0,"k":100}}]}],"ind":1},{"ty":4,"nm":"Polygon 1","sr":1,"st":0,"op":60,"ip":0,"hd":false,"ddd":0,"bm":0,"hasMask":false,"ao":0,"ks":{"a":{"a":0,"k":[0,25.000000000000014]},"s":{"a":1,"k":[{"o":{"x":0.167,"y":0.167},"i":{"x":0.833,"y":0.833},"s":[29.550491326302176,0],"t":0},{"o":{"x":0.167,"y":0.167},"i":{"x":0.833,"y":0.833},"s":[29.550491326302176,4],"t":20},{"s":[29.550491326302176,36.43099800139123],"t":40}]},"sk":{"a":0,"k":0},"p":{"a":0,"k":[21.90000000000001,39.83947757798817]},"r":{"a":0,"k":0},"sa":{"a":0,"k":0},"o":{"a":1,"k":[{"o":{"x":0.167,"y":0.167},"i":{"x":0.833,"y":0.833},"s":[100],"t":0},{"o":{"x":0.167,"y":0.167},"i":{"x":0.833,"y":0.833},"s":[100],"t":20},{"o":{"x":0.167,"y":0.167},"i":{"x":0.833,"y":0.833},"s":[100],"t":40},{"s":[0],"t":61}]}},"ef":[],"shapes":[{"ty":"gr","bm":0,"hd":false,"nm":"Group","it":[{"ty":"sr","bm":0,"hd":false,"nm":"Polygon Path 1","d":1,"pt":{"a":0,"k":3},"p":{"a":0,"k":[0,0]},"or":{"a":0,"k":50},"os":{"a":0,"k":0},"r":{"a":0,"k":0},"sy":2},{"ty":"fl","bm":0,"hd":false,"nm":"Fill","c":{"a":0,"k":[0.7373,0.9333,1]},"r":2,"o":{"a":0,"k":50}},{"ty":"tr","a":{"a":0,"k":[0,-12.499999999999986]},"s":{"a":0,"k":[100,100]},"sk":{"a":0,"k":0},"p":{"a":0,"k":[0,-12.499999999999986]},"r":{"a":0,"k":0},"sa":{"a":0,"k":0},"o":{"a":0,"k":100}}]}],"ind":2},{"ty":4,"nm":"Polygon 1","sr":1,"st":0,"op":60,"ip":0,"hd":false,"ddd":0,"bm":0,"hasMask":false,"ao":0,"ks":{"a":{"a":0,"k":[3.552713678800501e-15,25]},"s":{"a":1,"k":[{"o":{"x":0.167,"y":0.167},"i":{"x":0.833,"y":0.833},"s":[29.542499668321685,0],"t":0},{"o":{"x":0.167,"y":0.167},"i":{"x":0.833,"y":0.833},"s":[29.542499668321685,4],"t":20},{"s":[29.542499668321685,35.8460996801367],"t":40}]},"sk":{"a":0,"k":0},"p":{"a":0,"k":[7.000000000000022,40.178364369002566]},"r":{"a":0,"k":0},"sa":{"a":0,"k":0},"o":{"a":1,"k":[{"o":{"x":0.167,"y":0.167},"i":{"x":0.833,"y":0.833},"s":[100],"t":0},{"o":{"x":0.167,"y":0.167},"i":{"x":0.833,"y":0.833},"s":[100],"t":20},{"o":{"x":0.167,"y":0.167},"i":{"x":0.833,"y":0.833},"s":[100],"t":40},{"s":[0],"t":61}]}},"ef":[],"shapes":[{"ty":"gr","bm":0,"hd":false,"nm":"Group","it":[{"ty":"sr","bm":0,"hd":false,"nm":"Polygon Path 1","d":1,"pt":{"a":0,"k":3},"p":{"a":0,"k":[0,0]},"or":{"a":0,"k":50},"os":{"a":0,"k":0},"r":{"a":0,"k":0},"sy":2},{"ty":"fl","bm":0,"hd":false,"nm":"Fill","c":{"a":0,"k":[0.451,0.8431,0.9725]},"r":2,"o":{"a":0,"k":50}},{"ty":"tr","a":{"a":0,"k":[0,0]},"s":{"a":0,"k":[100,100]},"sk":{"a":0,"k":0},"p":{"a":0,"k":[0,0]},"r":{"a":0,"k":0},"sa":{"a":0,"k":0},"o":{"a":0,"k":100}}]}],"ind":3},{"ty":4,"nm":"Polygon 1","sr":1,"st":0,"op":60,"ip":0,"hd":false,"ddd":0,"bm":0,"hasMask":false,"ao":0,"ks":{"a":{"a":0,"k":[0,25.00000000000003]},"s":{"a":1,"k":[{"o":{"x":0.167,"y":0.167},"i":{"x":0.833,"y":0.833},"s":[46.45821845162052,0],"t":0},{"o":{"x":0.167,"y":0.167},"i":{"x":0.833,"y":0.833},"s":[46.45821845162052,6],"t":20},{"s":[46.45821845162052,54.32414041568423],"t":40}]},"sk":{"a":0,"k":0},"p":{"a":0,"k":[19.700000000000003,39.893577632794084]},"r":{"a":0,"k":0},"sa":{"a":0,"k":0},"o":{"a":1,"k":[{"o":{"x":0.167,"y":0.167},"i":{"x":0.833,"y":0.833},"s":[100],"t":0},{"o":{"x":0.167,"y":0.167},"i":{"x":0.833,"y":0.833},"s":[100],"t":20},{"o":{"x":0.167,"y":0.167},"i":{"x":0.833,"y":0.833},"s":[100],"t":40},{"s":[0],"t":61}]}},"ef":[],"shapes":[{"ty":"gr","bm":0,"hd":false,"nm":"Group","it":[{"ty":"sr","bm":0,"hd":false,"nm":"Polygon Path 1","d":1,"pt":{"a":0,"k":3},"p":{"a":0,"k":[0,0]},"or":{"a":0,"k":50},"os":{"a":0,"k":0},"r":{"a":0,"k":0},"sy":2},{"ty":"fl","bm":0,"hd":false,"nm":"Fill","c":{"a":0,"k":[0.451,0.8431,0.9725]},"r":2,"o":{"a":0,"k":70}},{"ty":"tr","a":{"a":0,"k":[0,-12.5]},"s":{"a":0,"k":[100,100]},"sk":{"a":0,"k":0},"p":{"a":0,"k":[0,-12.5]},"r":{"a":0,"k":0},"sa":{"a":0,"k":0},"o":{"a":0,"k":100}}]}],"ind":4},{"ty":4,"nm":"Polygon 1","sr":1,"st":0,"op":60,"ip":0,"hd":false,"ddd":0,"bm":0,"hasMask":false,"ao":0,"ks":{"a":{"a":0,"k":[1.4210854715202004e-14,25]},"s":{"a":1,"k":[{"o":{"x":0.167,"y":0.167},"i":{"x":0.833,"y":0.833},"s":[39.46693315064851,0],"t":0},{"o":{"x":0.167,"y":0.167},"i":{"x":0.833,"y":0.833},"s":[39.46693315064851,6],"t":20},{"s":[39.46693315064851,48.90527354130175],"t":40}]},"sk":{"a":0,"k":0},"p":{"a":0,"k":[27.800000000000015,40.09197387889941]},"r":{"a":0,"k":0},"sa":{"a":0,"k":0},"o":{"a":1,"k":[{"o":{"x":0.167,"y":0.167},"i":{"x":0.833,"y":0.833},"s":[100],"t":0},{"o":{"x":0.167,"y":0.167},"i":{"x":0.833,"y":0.833},"s":[100],"t":20},{"o":{"x":0.167,"y":0.167},"i":{"x":0.833,"y":0.833},"s":[100],"t":40},{"s":[0],"t":61}]}},"ef":[],"shapes":[{"ty":"gr","bm":0,"hd":false,"nm":"Group","it":[{"ty":"sr","bm":0,"hd":false,"nm":"Polygon Path 1","d":1,"pt":{"a":0,"k":3},"p":{"a":0,"k":[0,0]},"or":{"a":0,"k":50},"os":{"a":0,"k":0},"r":{"a":0,"k":0},"sy":2},{"ty":"fl","bm":0,"hd":false,"nm":"Fill","c":{"a":0,"k":[0.451,0.8431,0.9725]},"r":2,"o":{"a":0,"k":50}},{"ty":"tr","a":{"a":0,"k":[0,0]},"s":{"a":0,"k":[100,100]},"sk":{"a":0,"k":0},"p":{"a":0,"k":[0,0]},"r":{"a":0,"k":0},"sa":{"a":0,"k":0},"o":{"a":0,"k":100}}]}],"ind":5}],"v":"5.7.0","fr":60,"op":60,"ip":0,"assets":[]}